hca_to_scea/__init__.py
hca_to_scea/hca2scea.py
hca_to_scea/test_hca2scea.py
hca_to_scea/helpers/__init__.py
hca_to_scea/helpers/cell_lines.py
hca_to_scea/helpers/check_experimental_design.py
hca_to_scea/helpers/fetch_fastq_path.py
hca_to_scea/helpers/get_protocol_map.py
hca_to_scea/helpers/multitab_excel_to_single_txt.py
hca_to_scea/helpers/parse_xml.py
hca_to_scea/helpers/split_dataset.py
hca_to_scea/helpers/utils.py
hca2scea-0.1.1.dist-info/METADATA
hca2scea-0.1.1.dist-info/WHEEL
hca2scea-0.1.1.dist-info/entry_points.txt
hca2scea-0.1.1.dist-info/top_level.txt
hca2scea-0.1.1.dist-info/RECORD
