Metadata-Version: 2.1
Name: hca2scea
Version: 0.1.1
Summary: A tool to assist in the automatic conversion of hca metadata to scea metadata MAGE-TAB files.
Home-page: https://github.com/ebi-ait/hca-to-scea-tools
Author: Ami Day, Yusra Haider, Alegria Aclan, Javier Ferrer
Author-email: ami@ebi.ac.uk, yhaider@ebi.ac.uk, aaclan@ebi.ac.uk, javier.f.g@um.es
License: UNKNOWN
Platform: UNKNOWN
Classifier: Programming Language :: Python :: 3.7
Classifier: License :: OSI Approved :: Apache Software License
Requires-Dist: pandas
Requires-Dist: openpyxl
Requires-Dist: requests
Requires-Dist: numpy
Requires-Dist: tqdm
